{
  "matches": [
    {
      "name": " Man United vs Everton ",
      "start": "2025-11-25T05:00:00+09:00",
      "duration": 2.2,
      "link": " https://blog.cricfoot.net/?yosintv=manunited "
    },


    {
      "name": " Espanyol vs Sevilla ",
      "start": "2025-11-25T05:00:00+09:00",
      "duration": 2.2,
      "link": " https://blog.cricfoot.net/?yosintv=sevilla "
    },


    {
      "name": " Internacional vs Santos ",
      "start": "2025-11-25T09:00:00+09:00",
      "duration": 2.2,
      "link": " https://blog.cricfoot.net/?yosintv=santos "
    }
  ]
}
