{
  "matches": [
    {
      "name": "Crystal Palace vs Liverpool",
      "start": "2025-08-10T23:00:00+09:00",
      "duration": 2.6,
      "link": "https://blog.cricfoot.net/?yosintv=liverpool"
    },


    {
      "name": "Chelsea vs Milan",
      "start": "2025-08-10T23:00:00+09:00",
      "duration": 2.6,
      "link": "https://blog.cricfoot.net/?yosintv=chelsea"
    },


    {
      "name": "Dortmund vs Juventus",
      "start": "2025-08-11T00:30:00+09:00",
      "duration": 2.6,
      "link": "https://blog.cricfoot.net/?yosintv=dortund"
    },


    {
      "name": "Almería vs Al Nassr",
      "start": "2025-08-11T02:00:00+09:00",
      "duration": 2.6,
      "link": "https://blog.cricfoot.net/?yosintv=alnassr"
    },


    {
      "name": "Barcelona vs Como",
      "start": "2025-08-11T03:00:00+09:00",
      "duration": 2.6,
      "link": "https://blog.cricfoot.net/?yosintv=barcelona"
    },


    {
      "name": "Villarreal vs Aston Villa",
      "start": "2025-08-11T04:00:00+09:00",
      "duration": 2.6,
      "link": "https://blog.cricfoot.net/?yosintv=astonvilla"
    },


    {
      "name": "Cruzeiro vs Santos",
      "start": "2025-08-11T06:30:00+09:00",
      "duration": 2.6,
      "link": "https://blog.cricfoot.net/?yosintv=santos"
    },


    {
      "name": "Orlando vs Inter Miami",
      "start": "2025-08-11T09:00:00+09:00",
      "duration": 2.6,
      "link": "https://blog.cricfoot.net/?yosintv=intermiami"
    }
  ]
}
