  {
    "matches": [
      {
        "name": "Al Hilal vs Persepolis",
        "start": "2025-02-05T03:00:00+09:00",
        "duration": "2.5",
        "link": "https://blog.cricfoot.net/?yosintv=alhilal"
      },
      
      
      {
        "name": "Atalanta vs Bologna",
        "start": "2025-02-05T05:00:00+09:00",
        "duration": "2.5",
        "link": "https://blog.cricfoot.net/?yosintv=atalanta"
      },
      
      
      {
        "name": "Le Mans vs PSG",
        "start": "2025-02-05T05:10:00+09:00",
        "duration": "2.5",
        "link": "https://blog.cricfoot.net/?yosintv=psg"
      },
      
      
      {
        "name": "Atlético Madrid vs Getafe",
        "start": "2025-02-05T05:30:00+09:00",
        "duration": "2.5",
        "link": "https://blog.cricfoot.net/?yosintv=atletico"
      }
    ]
  }
