{
  "matches": [
    {
      "name": " Osasuna vs Sevilla ",
      "start": "2025-04-25T02:00:00+09:00",
      "duration": "2.6",
      "link": " https://yosintv2.github.io/ads/midst.html?url=_____ "
    },
    
    
    {
      "name": " Leganés vs Girona ",
      "start": "2025-04-25T02:00:00+09:00",
      "duration": "2.6",
      "link": " https://yosintv2.github.io/ads/midst.html?url=_____ "
    },
    
    
    {
      "name": " Bologna vs Empoli ",
      "start": "2025-04-25T04:00:00+09:00",
      "duration": "2.6",
      "link": " https://yosintv2.github.io/ads/midst.html?url=_____ "
    }
  ]
}
